concat/__init__.py
concat_ls-1.2.0.dist-info/LICENSE
concat_ls-1.2.0.dist-info/METADATA
concat_ls-1.2.0.dist-info/WHEEL
concat_ls-1.2.0.dist-info/top_level.txt
concat_ls-1.2.0.dist-info/RECORD
