Metadata-Version: 2.1
Name: concat-ls
Version: 1.2.0
Summary: Repository for ConCat: a simple and intuitive method for English lexical substitution.
Author-email: Juraj Vladika <juraj.vladika@tum.de>, Stephen Meisenbacher <stephen.meisenbacher@tum.de>
Maintainer-email: Juraj Vladika <juraj.vladika@tum.de>, Stephen Meisenbacher <stephen.meisenbacher@tum.de>
License: MIT License
Project-URL: Homepage, https://github.com/sebischair/ConCat
Project-URL: Documentation, https://github.com/sebischair/ConCat
Project-URL: Repository, https://github.com/sebischair/ConCat
Project-URL: Issues, https://github.com/sebischair/ConCat/issues
Keywords: lexical substitution,lexical semantics,word representation,natural language processing
Classifier: Programming Language :: Python :: 3
Classifier: License :: OSI Approved :: MIT License
Classifier: Operating System :: OS Independent
Requires-Python: >=3.6
License-File: LICENSE
Requires-Dist: nltk
Requires-Dist: numpy
Requires-Dist: spacy
Requires-Dist: torch
Requires-Dist: transformers
